{
  "114":{
    "PRE":{
      "mn":700.91,
      "ct":177553,
      "mx":749.241,
      "av":725.493
    },
    "WD":{
      "most_common":null
    },
    "Season":"winter",
    "Last_UTC":"2019-03-24T09:03:23Z",
    "AT":{
      "mn":-96.804,
      "ct":17752,
      "mx":-15.505,
      "av":-64.982
    },
    "First_UTC":"2019-03-23T08:23:48Z"
  },
  "108":{
    "PRE":{
      "mn":697.541,
      "ct":303863,
      "mx":750.386,
      "av":724.529
    },
    "WD":{
      "11":{
        "compass_right":-0.923879532511,
        "compass_up":-0.382683432365,
        "compass_degrees":247.5,
        "compass_point":"WSW",
        "ct":423
      },
      "10":{
        "compass_right":-0.707106781187,
        "compass_up":-0.707106781187,
        "compass_degrees":225.0,
        "compass_point":"SW",
        "ct":4628
      },
      "13":{
        "compass_right":-0.923879532511,
        "compass_up":0.382683432365,
        "compass_degrees":292.5,
        "compass_point":"WNW",
        "ct":201
      },
      "12":{
        "compass_right":-1.0,
        "compass_up":-0.0,
        "compass_degrees":270.0,
        "compass_point":"W",
        "ct":1230
      },
      "15":{
        "compass_right":-0.382683432365,
        "compass_up":0.923879532511,
        "compass_degrees":337.5,
        "compass_point":"NNW",
        "ct":61
      },
      "14":{
        "compass_right":-0.707106781187,
        "compass_up":0.707106781187,
        "compass_degrees":315.0,
        "compass_point":"NW",
        "ct":159
      },
      "1":{
        "compass_right":0.382683432365,
        "compass_up":0.923879532511,
        "compass_degrees":22.5,
        "compass_point":"NNE",
        "ct":92
      },
      "0":{
        "compass_right":0.0,
        "compass_up":1.0,
        "compass_degrees":0.0,
        "compass_point":"N",
        "ct":164
      },
      "3":{
        "compass_right":0.923879532511,
        "compass_up":0.382683432365,
        "compass_degrees":67.5,
        "compass_point":"ENE",
        "ct":155
      },
      "2":{
        "compass_right":0.707106781187,
        "compass_up":0.707106781187,
        "compass_degrees":45.0,
        "compass_point":"NE",
        "ct":15
      },
      "5":{
        "compass_right":0.923879532511,
        "compass_up":-0.382683432365,
        "compass_degrees":112.5,
        "compass_point":"ESE",
        "ct":35
      },
      "7":{
        "compass_right":0.382683432365,
        "compass_up":-0.923879532511,
        "compass_degrees":157.5,
        "compass_point":"SSE",
        "ct":743
      },
      "6":{
        "compass_right":0.707106781187,
        "compass_up":-0.707106781187,
        "compass_degrees":135.0,
        "compass_point":"SE",
        "ct":77
      },
      "9":{
        "compass_right":-0.382683432365,
        "compass_up":-0.923879532511,
        "compass_degrees":202.5,
        "compass_point":"SSW",
        "ct":4356
      },
      "8":{
        "compass_right":0.0,
        "compass_up":-1.0,
        "compass_degrees":180.0,
        "compass_point":"S",
        "ct":2399
      },
      "most_common":{
        "compass_right":-0.707106781187,
        "compass_up":-0.707106781187,
        "compass_degrees":225.0,
        "compass_point":"SW",
        "ct":4628
      }
    },
    "Season":"winter",
    "Last_UTC":"2019-03-17T22:44:50Z",
    "AT":{
      "mn":-96.075,
      "ct":32080,
      "mx":-14.416,
      "av":-51.452
    },
    "First_UTC":"2019-03-17T04:26:17Z",
    "HWS":{
      "mn":0.253,
      "ct":14738,
      "mx":12.282,
      "av":5.1
    }
  },
  "113":{
    "PRE":{
      "mn":700.393,
      "ct":177467,
      "mx":748.671,
      "av":724.937
    },
    "WD":{
      "most_common":null
    },
    "Season":"winter",
    "Last_UTC":"2019-03-23T08:23:48Z",
    "AT":{
      "mn":-96.664,
      "ct":17755,
      "mx":-15.338,
      "av":-64.606
    },
    "First_UTC":"2019-03-22T07:44:13Z"
  }
}